astronomica/__init__.py
astronomica/astronomica.py
astronomica/libconversion.py
astronomica/suntiming.py
astronomica-0.0.9.dist-info/LICENSE
astronomica-0.0.9.dist-info/METADATA
astronomica-0.0.9.dist-info/WHEEL
astronomica-0.0.9.dist-info/top_level.txt
astronomica-0.0.9.dist-info/RECORD
