Metadata-Version: 2.1
Name: astronomica
Version: 0.0.9
Summary: A Python library that deals with astronomy and mathematical calculations. It also helps with Julian Dates
Home-page: https://github.com/PyndyalaCoder/astronomica
Author: Siddhu Pendyala
Author-email: elcientifico.pendyala@gmail.com
License: MIT
Project-URL: Bug Tracker, https://github.com/PyndyalaCoder/astronomica/issues
License-File: LICENSE
Requires-Dist: astroquery
Requires-Dist: requests
Requires-Dist: astropy
Requires-Dist: skyfield
Requires-Dist: matplotlib
